pinnedimportlinter/__init__.py
pinnedimportlinter/cli.py
pinnedimportlinter/py.typed
pinnedimportlinter/application/__init__.py
pinnedimportlinter/application/config_parser.py
pinnedimportlinter/application/printer.py
pinnedimportlinter/application/rule_checker.py
pinnedimportlinter/application/use_cases/__init__.py
pinnedimportlinter/application/use_cases/checker_files_content.py
pinnedimportlinter/application/use_cases/walk.py
pinnedimportlinter/domain/__init__.py
pinnedimportlinter/domain/constant.py
pinnedimportlinter/domain/linter.py
pinned_import_linter-1.1.0.dist-info/LICENSE
pinned_import_linter-1.1.0.dist-info/METADATA
pinned_import_linter-1.1.0.dist-info/WHEEL
pinned_import_linter-1.1.0.dist-info/entry_points.txt
pinned_import_linter-1.1.0.dist-info/top_level.txt
pinned_import_linter-1.1.0.dist-info/RECORD
