Metadata-Version: 2.1
Name: pinned-import-linter
Version: 1.1.0
Summary: A plugin for python that will help you standardize imports from any libraries.
Author-email: Danil Gubanov <20949800+maintainer64@users.noreply.github.com>
License: MIT LICENSE
Project-URL: Source-code, https://github.com/maintainer64/pinned-import-linter/
Classifier: Intended Audience :: Developers
Classifier: Operating System :: Microsoft :: Windows
Classifier: Operating System :: POSIX
Classifier: Operating System :: Unix
Classifier: Programming Language :: Python
Classifier: Programming Language :: Python :: 3 :: Only
Classifier: Programming Language :: Python :: 3.8
Classifier: Programming Language :: Python :: 3.9
Classifier: Programming Language :: Python :: 3.10
Classifier: Programming Language :: Python :: 3.11
Classifier: Programming Language :: Python :: 3.12
Classifier: Programming Language :: Python :: Implementation :: CPython
Classifier: Topic :: Utilities
Requires-Python: >=3.8
License-File: LICENSE
